napari_compressed_labels_io/__init__.py
napari_compressed_labels_io/_reader.py
napari_compressed_labels_io/_version.py
napari_compressed_labels_io/_writer.py
napari_compressed_labels_io/_tests/__init__.py
napari_compressed_labels_io/_tests/test_reader.py
napari_compressed_labels_io/_tests/test_writer.py
napari_compressed_labels_io-0.0.2.dist-info/LICENSE
napari_compressed_labels_io-0.0.2.dist-info/METADATA
napari_compressed_labels_io-0.0.2.dist-info/WHEEL
napari_compressed_labels_io-0.0.2.dist-info/entry_points.txt
napari_compressed_labels_io-0.0.2.dist-info/top_level.txt
napari_compressed_labels_io-0.0.2.dist-info/RECORD
