Metadata-Version: 2.1
Name: napari-compressed-labels-io
Version: 0.0.2
Summary: Plugin exploring different options for reading and writing compressed and portable labels layers in napari.
Home-page: https://github.com/DragaDoncila/napari-compressed-labels-io
Author: Draga Doncila
Author-email: ddoncila@gmail.com
License: MIT
Platform: UNKNOWN
Classifier: Development Status :: 4 - Beta
Classifier: Intended Audience :: Developers
Classifier: Framework :: napari
Classifier: Topic :: Software Development :: Testing
Classifier: Programming Language :: Python
Classifier: Programming Language :: Python :: 3
Classifier: Programming Language :: Python :: 3.7
Classifier: Programming Language :: Python :: 3.8
Classifier: Programming Language :: Python :: 3.9
Classifier: Operating System :: OS Independent
Classifier: License :: OSI Approved :: MIT License
Requires-Python: >=3.6
Requires-Dist: napari-plugin-engine (>=0.1.4)
Requires-Dist: numpy
Requires-Dist: zarr
Requires-Dist: dask[complete]
